zzlog/__init__.py
zzlog/zzlog.py
zzlog-1.1.0.dist-info/licenses/LICENSE
zzlog-1.1.0.dist-info/METADATA
zzlog-1.1.0.dist-info/WHEEL
zzlog-1.1.0.dist-info/top_level.txt
zzlog-1.1.0.dist-info/RECORD
