Metadata-Version: 2.4
Name: zzlog
Version: 1.1.0
Summary: Logging setup made izzy
Home-page: https://github.com/pierre-rouanet/zzlog
Author: Pierre Rouanet
Author-email: pierre.rouanet@gmail.com
Requires-Python: >=3.5
License-File: LICENSE
Requires-Dist: python-json-logger
Dynamic: author
Dynamic: author-email
Dynamic: description
Dynamic: description-content-type
Dynamic: home-page
Dynamic: license-file
Dynamic: requires-dist
Dynamic: requires-python
Dynamic: summary
